LICENSE.txt
MANIFEST.in
README.rst
build_lib.bat
build_lib.sh
clean.sh
setup.py
PFNET.egg-info/PKG-INFO
PFNET.egg-info/SOURCES.txt
PFNET.egg-info/dependency_links.txt
PFNET.egg-info/not-zip-safe
PFNET.egg-info/requires.txt
PFNET.egg-info/top_level.txt
data/case118.m
data/case118.mat
data/case1354.mat
data/case300.m
data/case3012wp.mat
data/ieee14.m
data/ieee300.mat
data/sys_problem2.mat
data/sys_problem3.mat
docs/Makefile
docs/conf.py
docs/defs.hrst
docs/extensions.rst
docs/index.rst
docs/networks.rst
docs/papers.rst
docs/parsers.rst
docs/problems.rst
docs/reference.rst
docs/start.rst
docs/_templates/layout.html
examples/constraints.py
examples/contingencies.py
examples/custom_constraint_template.py
examples/custom_function_template.py
examples/functions.py
examples/modifications.py
examples/multi_period.py
examples/networks.py
examples/parsers.py
examples/power_flow.py
examples/problems.py
examples/projections.py
examples/start.py
examples/variables.py
lib/pfnet-1.3.5.tar.gz
pfnet/__init__.py
pfnet/cbat.pxd
pfnet/cbat.pyx
pfnet/cbranch.pxd
pfnet/cbranch.pyx
pfnet/cbranch_dc.pxd
pfnet/cbranch_dc.pyx
pfnet/cbrycor.pxd
pfnet/cbrycor.pyx
pfnet/cbus.pxd
pfnet/cbus.pyx
pfnet/cbus_dc.pxd
pfnet/cbus_dc.pyx
pfnet/cconstants.pxd
pfnet/cconstr.pxd
pfnet/cconstr.pyx
pfnet/ccont.pxd
pfnet/ccont.pyx
pfnet/cconv_csc.pxd
pfnet/cconv_csc.pyx
pfnet/cconv_vsc.pxd
pfnet/cconv_vsc.pyx
pfnet/cfacts.pxd
pfnet/cfacts.pyx
pfnet/cflags.pxd
pfnet/cfunc.pxd
pfnet/cfunc.pyx
pfnet/cgen.pxd
pfnet/cgen.pyx
pfnet/cheur.pxd
pfnet/cheur.pyx
pfnet/cload.pxd
pfnet/cload.pyx
pfnet/cmat.pxd
pfnet/cnet.pxd
pfnet/cnet.pyx
pfnet/cobjs.pxd
pfnet/cparser.pxd
pfnet/cparser.pyx
pfnet/cparser_epc.pxd
pfnet/cparser_raw.pxd
pfnet/cpfnet.pyx
pfnet/cprob.pxd
pfnet/cprob.pyx
pfnet/cshunt.pxd
pfnet/cshunt.pyx
pfnet/cstrings.pyx
pfnet/cvargen.pxd
pfnet/cvargen.pyx
pfnet/cvec.pxd
pfnet/json_utils.py
pfnet/version.py
pfnet/constraints/__init__.py
pfnet/constraints/dummy_constraint.py
pfnet/functions/__init__.py
pfnet/functions/dummy_function.py
pfnet/parsers/__init__.py
pfnet/parsers/parser_mat.py
pfnet/tests/__init__.py
pfnet/tests/utils.py
pfnet/utils/__init__.py
pfnet/utils/ptdf.py
