Metadata-Version: 1.1
Name: PFNET
Version: 1.3.5rc1
Summary: Power Flow Network Library
Home-page: https://github.com/ttinoco/PFNET
Author: Tomas Tinoco De Rubira
Author-email: ttinoco5687@gmail.com
License: BSD 2-Clause License
Platform: UNKNOWN
Classifier: Development Status :: 5 - Production/Stable
Classifier: License :: OSI Approved :: BSD License
Classifier: Programming Language :: Python :: 2.7
Classifier: Programming Language :: Python :: 3.6
